src/__init__.py
src/main.py
custom_package1234567-0.2.dist-info/METADATA
custom_package1234567-0.2.dist-info/WHEEL
custom_package1234567-0.2.dist-info/entry_points.txt
custom_package1234567-0.2.dist-info/top_level.txt
custom_package1234567-0.2.dist-info/RECORD
