Metadata-Version: 2.4
Name: custom_package1234567
Version: 0.2
Dynamic: description
Dynamic: description-content-type
